tradingtoolbox/__init__.py
tradingtoolbox/rs.abi3.so
tradingtoolbox/clickhouse/__init__.py
tradingtoolbox/clickhouse/clickhouse_async.py
tradingtoolbox/clickhouse/clickhouse_sync.py
tradingtoolbox/clickhouse/generate_table_schema.py
tradingtoolbox/exchanges/__init__.py
tradingtoolbox/exchanges/binance.py
tradingtoolbox/exchanges/contract.py
tradingtoolbox/exchanges/exchange.py
tradingtoolbox/exchanges/exchange_base.py
tradingtoolbox/exchanges/exchange_config.py
tradingtoolbox/exchanges/exchange_ohlcv.py
tradingtoolbox/exchanges/exchange_trades.py
tradingtoolbox/exchanges/okx.py
tradingtoolbox/rs/rs.pyi
tradingtoolbox/utils/__init__.py
tradingtoolbox/utils/cache.py
tradingtoolbox/utils/logger.py
tradingtoolbox/utils/resample.py
tradingtoolbox/utils/time_manip.py
tradingtoolbox-0.53.0.dist-info/METADATA
tradingtoolbox-0.53.0.dist-info/WHEEL
tradingtoolbox-0.53.0.dist-info/licenses/LICENSE.txt
tradingtoolbox-0.53.0.dist-info/RECORD
