Metadata-Version: 2.4
Name: tradingtoolbox
Version: 0.53.0
Summary: Add your description here
Author: Alpha Zen
License: MIT
License-File: LICENSE.txt
Requires-Python: >=3.9
Requires-Dist: arrow>=1.3.0
Requires-Dist: ccxt>=4.4.12
Requires-Dist: clickhouse-connect>=0.7.16
Requires-Dist: loguru>=0.7.2
Requires-Dist: msgspec>=0.18.6
Requires-Dist: orjson>=3.10.6
Requires-Dist: pandas>=2.2.2
Requires-Dist: pyarrow>=17.0.0
Requires-Dist: pydantic>=2.9.2
Requires-Dist: pytest-asyncio>=0.24.0
Requires-Dist: python-binance>=1.0.19
Requires-Dist: python-dateutil>=2.9.0.post0
Requires-Dist: rich>=13.8.1
Requires-Dist: uvloop>=0.20.0
